llama_index/storage/index_store/couchbase/__init__.py
llama_index/storage/index_store/couchbase/base.py
llama_index_index_store_couchbase-0.3.1.dist-info/METADATA
llama_index_index_store_couchbase-0.3.1.dist-info/WHEEL
llama_index_index_store_couchbase-0.3.1.dist-info/licenses/LICENSE
llama_index_index_store_couchbase-0.3.1.dist-info/RECORD
