Metadata-Version: 2.4
Name: llama-index-index-store-couchbase
Version: 0.3.1
Summary: llama-index index_store couchbase integration
Author-email: Couchbase <devadvocates@couchbase.com>
License-Expression: MIT
License-File: LICENSE
Requires-Python: <4.0,>=3.9
Requires-Dist: llama-index-core<0.15,>=0.13.0
Requires-Dist: llama-index-kvstore-couchbase<0.4,>=0.3.0
